AUTHORS
LICENSE
MANIFEST.in
README.rst
setup.py
Eve_docs.egg-info/PKG-INFO
Eve_docs.egg-info/SOURCES.txt
Eve_docs.egg-info/dependency_links.txt
Eve_docs.egg-info/not-zip-safe
Eve_docs.egg-info/requires.txt
Eve_docs.egg-info/top_level.txt
eve_docs/__init__.py
eve_docs/config.py
eve_docs/labels.py
eve_docs/templates/evedocstyle.html
eve_docs/templates/index.html
eve_docs/templates/macros.html