Metadata-Version: 1.1
Name: Eve-docs
Version: 0.1.1
Summary: Generates documentation for Eve APIs
Home-page: https://github.com/charlesflynn/eve-docs
Author: Charles Flynn
Author-email: git@irab.org
License: The MIT License
